shoper/__init__.py
shoper/shelloperator.py
shoper-1.4.4.dist-info/METADATA
shoper-1.4.4.dist-info/WHEEL
shoper-1.4.4.dist-info/licenses/LICENSE
shoper-1.4.4.dist-info/RECORD
