Metadata-Version: 2.4
Name: shoper
Version: 1.4.4
Summary: Simple shell operator module
Project-URL: Repository, https://github.com/dceoy/shoper.git
Author-email: Daichi Narushima <dceoy@users.noreply.github.com>
Maintainer-email: Daichi Narushima <dceoy@users.noreply.github.com>
License-Expression: MIT
License-File: LICENSE
Classifier: Operating System :: MacOS
Classifier: Operating System :: POSIX :: Linux
Classifier: Programming Language :: Python
Classifier: Programming Language :: Python :: 3
Classifier: Topic :: System :: Shells
Requires-Python: >=3.10
